cvproxy/__init__.py
cvproxy/__main__.py
cvproxy/cvproxy.py
cvproxy-1.0.4.dist-info/licenses/LICENSE
cvproxy-1.0.4.dist-info/METADATA
cvproxy-1.0.4.dist-info/WHEEL
cvproxy-1.0.4.dist-info/entry_points.txt
cvproxy-1.0.4.dist-info/top_level.txt
cvproxy-1.0.4.dist-info/RECORD
