Metadata-Version: 2.4
Name: cvproxy
Version: 1.0.4
Summary: CVProxy - CloudVision Proxy
Author-email: Chris Mason <chris@netnix.org>
License-Expression: MIT
Project-URL: Repository, https://github.com/cmason3/cvproxy.git
Project-URL: Issues, https://github.com/cmason3/cvproxy/issues
Project-URL: Changelog, https://github.com/cmason3/cvproxy/blob/main/CHANGELOG.md
Classifier: Development Status :: 4 - Beta
Classifier: Programming Language :: Python :: 3
Requires-Python: >=3.10
License-File: LICENSE
Requires-Dist: pyavd>=5.7.2
Requires-Dist: jsonschema
Dynamic: license-file
